hformat/__init__.py
hformat/linter.py
hformat/main.py
demo_hformat-0.0.3.dist-info/LICENSE
demo_hformat-0.0.3.dist-info/METADATA
demo_hformat-0.0.3.dist-info/WHEEL
demo_hformat-0.0.3.dist-info/entry_points.txt
demo_hformat-0.0.3.dist-info/top_level.txt
demo_hformat-0.0.3.dist-info/RECORD
